{
  "_class": "symbolInstance",
  "booleanOperation": -1,
  "clippingMaskMode": 0,
  "do_objectID": "F36BD780-8AD6-4EBD-B656-5259013AA419",
  "exportOptions": {
    "_class": "exportOptions",
    "do_objectID": "974F4B52-06F6-4E6B-AD85-7B7083D913A8",
    "exportFormats": [
    ],
    "includedLayerIds": [
    ],
    "layerOptions": 0,
    "shouldTrim": false
  },
  "frame": {
    "_class": "rect",
    "constrainProportions": false,
    "do_objectID": "98B6D371-6ABC-48DE-AD68-177C75930958",
    "height": 25,
    "width": 246,
    "x": 1129,
    "y": 55
  },
  "hasClippingMask": false,
  "horizontalSpacing": 0,
  "isFixedToViewport": false,
  "isFlippedHorizontal": false,
  "isFlippedVertical": false,
  "isLocked": false,
  "isVisible": true,
  "layerListExpandedType": 0,
  "name": "search copy",
  "nameIsFixed": false,
  "overrideValues": [
  ],
  "resizingConstraint": 63,
  "resizingType": 0,
  "rotation": 0,
  "scale": 1,
  "shouldBreakMaskChain": false,
  "style": {
    "_class": "style",
    "do_objectID": "217DBECF-7674-4CDF-8560-A1B47BAC3A52",
    "endMarkerType": 0,
    "miterLimit": 10,
    "startMarkerType": 0,
    "windingRule": 1
  },
  "symbolID": "E0DDC56D-BA89-488B-87A3-13186AC48556",
  "verticalSpacing": 0
}