{
  "_class": "text",
  "attributedString": {
    "_class": "attributedString",
    "attributes": [
      {
        "_class": "stringAttribute",
        "attributes": {
          "MSAttributedStringColorAttribute": {
            "_class": "color",
            "alpha": 1,
            "blue": 0,
            "green": 0,
            "red": 0
          },
          "MSAttributedStringFontAttribute": {
            "_class": "fontDescriptor",
            "attributes": {
              "name": "BebasNeue-Regular",
              "size": 32
            }
          },
          "paragraphStyle": {
            "_class": "paragraphStyle"
          },
          "strikethroughStyle": 0,
          "underlineStyle": 1
        },
        "length": 9,
        "location": 0
      }
    ],
    "string": "Academics"
  },
  "automaticallyDrawOnUnderlyingPath": false,
  "booleanOperation": -1,
  "clippingMaskMode": 0,
  "do_objectID": "DF8BFE9B-F244-49D8-9A9F-7DB3740F08DF",
  "dontSynchroniseWithSymbol": false,
  "exportOptions": {
    "_class": "exportOptions",
    "do_objectID": "B8B5B303-8E47-46A6-9B38-DC11FB43B304",
    "exportFormats": [
    ],
    "includedLayerIds": [
    ],
    "layerOptions": 0,
    "shouldTrim": false
  },
  "frame": {
    "_class": "rect",
    "constrainProportions": false,
    "do_objectID": "40A8FF40-51DB-4E04-9BD1-456BB9E13E41",
    "height": 39,
    "width": 112,
    "x": 124,
    "y": 3268
  },
  "glyphBounds": "{{0, 6}, {110, 24}}",
  "hasClippingMask": false,
  "isFixedToViewport": false,
  "isFlippedHorizontal": false,
  "isFlippedVertical": false,
  "isLocked": false,
  "isVisible": true,
  "layerListExpandedType": 0,
  "lineSpacingBehaviour": 2,
  "name": "Academics Copy",
  "nameIsFixed": false,
  "resizingConstraint": 47,
  "resizingType": 0,
  "rotation": 0,
  "shouldBreakMaskChain": false,
  "style": {
    "_class": "style",
    "do_objectID": "F4E8778B-C46E-44DA-828A-4C6B48FE4574",
    "endMarkerType": 0,
    "miterLimit": 10,
    "startMarkerType": 0,
    "textStyle": {
      "_class": "textStyle",
      "do_objectID": "1FCD4273-68B7-4F18-9BD0-F97E2AC3472E",
      "encodedAttributes": {
        "MSAttributedStringColorAttribute": {
          "_class": "color",
          "alpha": 1,
          "blue": 0,
          "green": 0,
          "red": 0
        },
        "MSAttributedStringFontAttribute": {
          "_class": "fontDescriptor",
          "attributes": {
            "name": "BebasNeue-Regular",
            "size": 32
          }
        },
        "paragraphStyle": {
          "_class": "paragraphStyle"
        },
        "strikethroughStyle": 0,
        "underlineStyle": 1
      },
      "verticalAlignment": 0
    },
    "windingRule": 1
  },
  "textBehaviour": 1
}