{
  "_class": "symbolInstance",
  "booleanOperation": -1,
  "clippingMaskMode": 0,
  "do_objectID": "9F9964A5-AFD9-435E-8886-916BBF8E4E22",
  "exportOptions": {
    "_class": "exportOptions",
    "do_objectID": "E9DFE7BB-1D6F-4D4E-9AD3-DA52B957A17D",
    "exportFormats": [
    ],
    "includedLayerIds": [
    ],
    "layerOptions": 0,
    "shouldTrim": false
  },
  "frame": {
    "_class": "rect",
    "constrainProportions": false,
    "do_objectID": "07C6CD53-A121-4D9D-96E2-81E8BC058CFA",
    "height": 87,
    "width": 375,
    "x": 50,
    "y": 2341
  },
  "hasClippingMask": false,
  "horizontalSpacing": 0,
  "isFixedToViewport": false,
  "isFlippedHorizontal": false,
  "isFlippedVertical": false,
  "isLocked": false,
  "isVisible": true,
  "layerListExpandedType": 0,
  "name": "BUTTON 1 Copy",
  "nameIsFixed": false,
  "overrideValues": [
  ],
  "resizingConstraint": 63,
  "resizingType": 0,
  "rotation": 0,
  "scale": 1,
  "shouldBreakMaskChain": false,
  "style": {
    "_class": "style",
    "do_objectID": "10C53BF9-29F7-43A9-95EE-A0BF0C9EAD47",
    "endMarkerType": 0,
    "miterLimit": 10,
    "startMarkerType": 0,
    "windingRule": 1
  },
  "symbolID": "0115C16B-1BB5-469A-A4E5-F77AC6CA7B2B",
  "verticalSpacing": 0
}