{
  "_class": "symbolInstance",
  "booleanOperation": -1,
  "clippingMaskMode": 0,
  "do_objectID": "9BA19F64-0B36-4883-A62F-EF1392925501",
  "exportOptions": {
    "_class": "exportOptions",
    "do_objectID": "32F825FB-4F43-4672-B8BA-A265093F8FE6",
    "exportFormats": [
    ],
    "includedLayerIds": [
    ],
    "layerOptions": 0,
    "shouldTrim": false
  },
  "frame": {
    "_class": "rect",
    "constrainProportions": false,
    "do_objectID": "1B238B53-E793-4245-85DF-B28B79F4EECB",
    "height": 114.4444444444444,
    "width": 320,
    "x": 0,
    "y": 612.8883147367667
  },
  "hasClippingMask": false,
  "horizontalSpacing": 0,
  "isFixedToViewport": false,
  "isFlippedHorizontal": false,
  "isFlippedVertical": false,
  "isLocked": false,
  "isVisible": true,
  "layerListExpandedType": 0,
  "name": "footer",
  "nameIsFixed": false,
  "overrideValues": [
  ],
  "resizingConstraint": 63,
  "resizingType": 0,
  "rotation": 0,
  "scale": 0.2222222222222222,
  "shouldBreakMaskChain": false,
  "style": {
    "_class": "style",
    "blur": {
      "_class": "blur",
      "center": "{0.5, 0.5}",
      "do_objectID": "09BA6428-FD1C-4279-B336-91DC137AA73C",
      "isEnabled": false,
      "motionAngle": 0,
      "radius": 2.222222222222222,
      "saturation": 1,
      "type": 0
    },
    "do_objectID": "5E5C79CF-1041-4FF5-B1C6-26813273CDE2",
    "endMarkerType": 0,
    "miterLimit": 10,
    "startMarkerType": 0,
    "windingRule": 1
  },
  "symbolID": "38B953E0-7BD0-4954-B4BE-9F662D78E284",
  "verticalSpacing": 0
}