{
  "_class": "symbolInstance",
  "booleanOperation": -1,
  "clippingMaskMode": 0,
  "do_objectID": "E8E3C30A-BD7F-4874-9357-2A5527DE3649",
  "exportOptions": {
    "_class": "exportOptions",
    "do_objectID": "46A5319C-FAB7-475F-8266-CB9EE726B046",
    "exportFormats": [
    ],
    "includedLayerIds": [
    ],
    "layerOptions": 0,
    "shouldTrim": false
  },
  "frame": {
    "_class": "rect",
    "constrainProportions": false,
    "do_objectID": "AFDA1EA2-3D8B-4E90-909D-902655CED716",
    "height": 72.44444444444444,
    "width": 83.33333333333333,
    "x": 118.2222222222222,
    "y": 507.5549814034328
  },
  "hasClippingMask": false,
  "horizontalSpacing": 0,
  "isFixedToViewport": false,
  "isFlippedHorizontal": false,
  "isFlippedVertical": false,
  "isLocked": false,
  "isVisible": true,
  "layerListExpandedType": 0,
  "name": "pop up featured",
  "nameIsFixed": false,
  "overrideValues": [
  ],
  "resizingConstraint": 63,
  "resizingType": 0,
  "rotation": 0,
  "scale": 0.2222222222222222,
  "shouldBreakMaskChain": false,
  "style": {
    "_class": "style",
    "blur": {
      "_class": "blur",
      "center": "{0.5, 0.5}",
      "do_objectID": "C3C6355E-BA37-4B31-A63F-C1C3CD804069",
      "isEnabled": false,
      "motionAngle": 0,
      "radius": 2.222222222222222,
      "saturation": 1,
      "type": 0
    },
    "do_objectID": "839F6579-DB25-43DA-8E36-6CC007D6CD7B",
    "endMarkerType": 0,
    "miterLimit": 10,
    "startMarkerType": 0,
    "windingRule": 1
  },
  "symbolID": "B36BA8B0-C2A5-4710-80B3-2FC68C838C9C",
  "userInfo": {
    "com.invision.prototype": {
      "backgroundOpacity": 0,
      "closeOnClickOutside": 1,
      "componentType": "SRLink",
      "fixOverlayPosition": 1,
      "gesture": 0,
      "linkType": 0,
      "maintainScrollPositionAfterGesture": 0,
      "maintainScrollPositionAfterRedirect": 0,
      "openURLInNewWindow": 0,
      "overlayPosition": 0,
      "overlayTransition": 0,
      "redirectAfter": 0,
      "reverseTransitionOnClose": 1,
      "scrollToPosition": 0,
      "smoothScrolling": 0,
      "stayOnTargetScreen": 0,
      "targetArtboardID": "2F197246-BA13-4AFF-B909-038E9FDF6166",
      "transition": 0
    }
  },
  "verticalSpacing": 0
}