{
  "_class": "symbolInstance",
  "booleanOperation": -1,
  "clippingMaskMode": 0,
  "do_objectID": "620F0F27-010D-4B9B-B97F-7C3CE3500F96",
  "exportOptions": {
    "_class": "exportOptions",
    "do_objectID": "22B90BE2-E36A-4A07-9EA6-65769E2CA374",
    "exportFormats": [
    ],
    "includedLayerIds": [
    ],
    "layerOptions": 0,
    "shouldTrim": false
  },
  "frame": {
    "_class": "rect",
    "constrainProportions": false,
    "do_objectID": "14A14026-C5F3-4150-9A1F-5F98F24BADDD",
    "height": 170.2222222222222,
    "width": 363.1111111111111,
    "x": -21.33333333333333,
    "y": 18.7635123786941
  },
  "hasClippingMask": false,
  "horizontalSpacing": 0,
  "isFixedToViewport": false,
  "isFlippedHorizontal": false,
  "isFlippedVertical": false,
  "isLocked": false,
  "isVisible": true,
  "layerListExpandedType": 0,
  "name": "header",
  "nameIsFixed": false,
  "overrideValues": [
  ],
  "resizingConstraint": 63,
  "resizingType": 0,
  "rotation": 0,
  "scale": 0.2222222222222222,
  "shouldBreakMaskChain": false,
  "style": {
    "_class": "style",
    "blur": {
      "_class": "blur",
      "center": "{0.5, 0.5}",
      "do_objectID": "641033DA-4E9D-47F7-A4CD-7BEE279317B9",
      "isEnabled": false,
      "motionAngle": 0,
      "radius": 2.222222222222222,
      "saturation": 1,
      "type": 0
    },
    "do_objectID": "4367B9D9-6605-40FF-85D7-B47F160DEB15",
    "endMarkerType": 0,
    "miterLimit": 10,
    "startMarkerType": 0,
    "windingRule": 1
  },
  "symbolID": "1578B43B-C334-4319-9E28-3A602A611896",
  "verticalSpacing": 0
}