{
  "_class": "text",
  "attributedString": {
    "_class": "attributedString",
    "attributes": [
      {
        "_class": "stringAttribute",
        "attributes": {
          "MSAttributedStringColorAttribute": {
            "_class": "color",
            "alpha": 1,
            "blue": 0.207843137254902,
            "green": 0.1568627450980392,
            "red": 0.2
          },
          "MSAttributedStringFontAttribute": {
            "_class": "fontDescriptor",
            "attributes": {
              "name": "BebasNeue-Regular",
              "size": 32
            }
          },
          "paragraphStyle": {
            "_class": "paragraphStyle"
          }
        },
        "length": 7,
        "location": 0
      }
    ],
    "string": "Faculty"
  },
  "automaticallyDrawOnUnderlyingPath": false,
  "booleanOperation": -1,
  "clippingMaskMode": 0,
  "do_objectID": "07EFFEA9-07D3-4D2A-B673-B5A86009F78A",
  "dontSynchroniseWithSymbol": false,
  "exportOptions": {
    "_class": "exportOptions",
    "do_objectID": "CFE5A21E-278B-4F7E-8F96-927E3F7C457F",
    "exportFormats": [
    ],
    "includedLayerIds": [
    ],
    "layerOptions": 0,
    "shouldTrim": false
  },
  "frame": {
    "_class": "rect",
    "constrainProportions": false,
    "do_objectID": "30C237F7-AAED-4D0C-8033-84FD9A6EAB5A",
    "height": 39,
    "width": 81,
    "x": 420,
    "y": 50
  },
  "glyphBounds": "{{1, 6}, {80, 24}}",
  "hasClippingMask": false,
  "isFixedToViewport": false,
  "isFlippedHorizontal": false,
  "isFlippedVertical": false,
  "isLocked": false,
  "isVisible": true,
  "layerListExpandedType": 0,
  "lineSpacingBehaviour": 2,
  "name": "Faculty Copy 2",
  "nameIsFixed": false,
  "resizingConstraint": 47,
  "resizingType": 0,
  "rotation": 0,
  "shouldBreakMaskChain": false,
  "style": {
    "_class": "style",
    "do_objectID": "644E5A48-4AC0-4639-8F37-6C119558A41E",
    "endMarkerType": 0,
    "miterLimit": 10,
    "startMarkerType": 0,
    "textStyle": {
      "_class": "textStyle",
      "do_objectID": "8DA746B5-4814-4D0F-A82D-5FB84E59529E",
      "encodedAttributes": {
        "MSAttributedStringColorAttribute": {
          "_class": "color",
          "alpha": 1,
          "blue": 0.207843137254902,
          "green": 0.1568627450980392,
          "red": 0.2
        },
        "MSAttributedStringFontAttribute": {
          "_class": "fontDescriptor",
          "attributes": {
            "name": "BebasNeue-Regular",
            "size": 32
          }
        },
        "paragraphStyle": {
          "_class": "paragraphStyle"
        }
      },
      "verticalAlignment": 0
    },
    "windingRule": 1
  },
  "textBehaviour": 1,
  "userInfo": {
    "com.invision.prototype": {
      "backgroundOpacity": 0,
      "closeOnClickOutside": 1,
      "componentType": "SRLink",
      "fixOverlayPosition": 1,
      "gesture": 0,
      "linkType": 0,
      "maintainScrollPositionAfterGesture": 0,
      "maintainScrollPositionAfterRedirect": 0,
      "openURLInNewWindow": 0,
      "overlayPosition": 0,
      "overlayTransition": 0,
      "redirectAfter": 0,
      "reverseTransitionOnClose": 1,
      "scrollToPosition": 0,
      "smoothScrolling": 0,
      "stayOnTargetScreen": 0,
      "targetArtboardID": "3459CD31-ABC9-4E39-94F6-F2ADA6E18DCF",
      "transition": 0
    }
  }
}