{
  "_class": "group",
  "booleanOperation": -1,
  "clippingMaskMode": 0,
  "do_objectID": "5969AEF2-5798-42D0-AD09-1899F8AB84DC",
  "exportOptions": {
    "_class": "exportOptions",
    "do_objectID": "A87F1121-F9DF-433B-B179-A473ED873AB8",
    "exportFormats": [
    ],
    "includedLayerIds": [
    ],
    "layerOptions": 0,
    "shouldTrim": false
  },
  "frame": {
    "_class": "rect",
    "constrainProportions": false,
    "do_objectID": "6B75502A-8903-4B71-80E3-1DFAC943B8D1",
    "height": 445,
    "width": 480,
    "x": -5,
    "y": 2105
  },
  "hasClickThrough": false,
  "hasClippingMask": false,
  "isFixedToViewport": false,
  "isFlippedHorizontal": false,
  "isFlippedVertical": false,
  "isLocked": false,
  "isVisible": true,
  "layerListExpandedType": 0,
  "layers": [
    {
      "class": "rectangle",
      "id": "83EE0652-163F-4E6F-B6C6-EF1320D7F7E0"
    },
    {
      "class": "bitmap",
      "id": "5B23F699-F44F-4CB1-A5AC-C12CACF7CD0A"
    }
  ],
  "name": "Bitmap Copy",
  "nameIsFixed": false,
  "resizingConstraint": 63,
  "resizingType": 0,
  "rotation": 0,
  "shouldBreakMaskChain": false,
  "style": {
    "_class": "style",
    "do_objectID": "9762A4A9-5E38-44EA-8C7F-258F68A299C1",
    "endMarkerType": 0,
    "miterLimit": 10,
    "startMarkerType": 0,
    "windingRule": 1
  }
}